{
    "type": "FeatureCollection",
    "features": [
        {
            "type": "Feature",
            "geometry": {
                "type": "Point",
                "coordinates": [
                    -82.40321,
                    34.848204
                ]
            },
            "properties": {
                "title": "GHS Swamp Rabbit Trail",
                "mile_marker": "33 1\/2"
            }
        },
        {
            "type": "Feature",
            "geometry": {
                "type": "Point",
                "coordinates": [
                    -82.4119,
                    34.85065
                ]
            },
            "properties": {
                "title": "GHS Swamp Rabbit Trail",
                "mile_marker": "33"
            }
        },
        {
            "type": "Feature",
            "geometry": {
                "type": "Point",
                "coordinates": [
                    -82.416776,
                    34.854951
                ]
            },
            "properties": {
                "title": "GHS Swamp Rabbit Trail",
                "mile_marker": "32 1\/2"
            }
        },
        {
            "type": "Feature",
            "geometry": {
                "type": "Point",
                "coordinates": [
                    -82.4219708,
                    34.8681185
                ]
            },
            "properties": {
                "title": "GHS Swamp Rabbit Trail",
                "mile_marker": "31 1\/2"
            }
        },
        {
            "type": "Feature",
            "geometry": {
                "type": "Point",
                "coordinates": [
                    -82.423886,
                    34.8743511
                ]
            },
            "properties": {
                "title": "GHS Swamp Rabbit Trail",
                "mile_marker": "31"
            }
        },
        {
            "type": "Feature",
            "geometry": {
                "type": "Point",
                "coordinates": [
                    -82.4296,
                    34.8775
                ]
            },
            "properties": {
                "title": "GHS Swamp Rabbit Trail",
                "mile_marker": "30 1\/2"
            }
        },
        {
            "type": "Feature",
            "geometry": {
                "type": "Point",
                "coordinates": [
                    -82.4419,
                    34.8984
                ]
            },
            "properties": {
                "title": "GHS Swamp Rabbit Trail",
                "mile_marker": "29"
            }
        },
        {
            "type": "Feature",
            "geometry": {
                "type": "Point",
                "coordinates": [
                    -82.4445,
                    34.9052
                ]
            },
            "properties": {
                "title": "GHS Swamp Rabbit Trail",
                "mile_marker": "28 1\/2"
            }
        },
        {
            "type": "Feature",
            "geometry": {
                "type": "Point",
                "coordinates": [
                    -82.4475,
                    34.912
                ]
            },
            "properties": {
                "title": "GHS Swamp Rabbit Trail",
                "mile_marker": "28"
            }
        },
        {
            "type": "Feature",
            "geometry": {
                "type": "Point",
                "coordinates": [
                    -82.4456,
                    34.919
                ]
            },
            "properties": {
                "title": "GHS Swamp Rabbit Trail",
                "mile_marker": "27 1\/2"
            }
        },
        {
            "type": "Feature",
            "geometry": {
                "type": "Point",
                "coordinates": [
                    -82.4435,
                    34.9259
                ]
            },
            "properties": {
                "title": "GHS Swamp Rabbit Trail",
                "mile_marker": "27"
            }
        },
        {
            "type": "Feature",
            "geometry": {
                "type": "Point",
                "coordinates": [
                    -82.4424,
                    34.9331
                ]
            },
            "properties": {
                "title": "GHS Swamp Rabbit Trail",
                "mile_marker": "26 1\/2"
            }
        },
        {
            "type": "Feature",
            "geometry": {
                "type": "Point",
                "coordinates": [
                    -82.4208,
                    34.8615
                ]
            },
            "properties": {
                "title": "GHS Swamp Rabbit Trail",
                "mile_marker": "32"
            }
        }
    ]
}